{
	"tags": null,
	"ellipsoid": [
		0.5,
		1,
		0.5
	],
	"ellipsoidOffset": [
		0,
		0,
		0
	],
	"checkCollisions": true,
	"applyGravity": true,
	"rotation": [
		-0.12634597433486816,
		0.04075328247684231,
		-1.87032916786655e-9
	],
	"speed": 1.5,
	"position": [
		-29.490251541137695,
		6.97527551651001,
		-16.000499725341797
	],
	"upVector": [
		-0.005133901722729206,
		0.9920289516448975,
		-0.12590546905994415
	],
	"fov": 0.6,
	"minZ": 1,
	"maxZ": 1946195.068359375,
	"inertia": 0.9,
	"mode": 0,
	"layerMask": 268435455,
	"fovMode": 0,
	"cameraRigMode": 0,
	"name": "PlayerCamera",
	"id": "a34b79f0-f744-4f43-b3fc-9057868cd6f3",
	"state": "",
	"metadata": {
		"script": {
			"name": "src/scenes/MainMap/cameramove.ts",
			"properties": {
				"_forwardKey": {
					"type": "KeyMap",
					"value": 87
				},
				"_backwardKey": {
					"type": "KeyMap",
					"value": 83
				},
				"_upwardsKey": {
					"type": "KeyMap",
					"value": 32
				},
				"_strafeLeftKey": {
					"type": "KeyMap",
					"value": 65
				},
				"_strafeRightKey": {
					"type": "KeyMap",
					"value": 68
				},
				"_ballForceFactor": {
					"type": "number",
					"value": 1
				}
			}
		},
		"doNotExport": false
	},
	"type": "UniversalCamera",
	"inputsmgr": {
		"FreeCameraKeyboardMoveInput": {
			"tags": null,
			"keysUp": [
				75
			],
			"keysUpward": [
				33
			],
			"keysDown": [
				40
			],
			"keysDownward": [
				34
			],
			"keysLeft": [
				37
			],
			"keysRight": [
				39
			]
		},
		"FreeCameraMouseInput": {
			"tags": null,
			"buttons": [
				0,
				1,
				2
			],
			"angularSensibility": 2000
		}
	},
	"animations": [],
	"ranges": []
}