{
	"materials": [],
	"meshes": [
		{
			"name": "PM3D_Cube3D1_11",
			"id": "9e6bd45e-1f53-4272-86d7-108315fad75c",
			"uniqueId": 13,
			"type": "Mesh",
			"position": [
				0,
				10.062779426574707,
				0
			],
			"rotationQuaternion": [
				0,
				0,
				0,
				1
			],
			"scaling": [
				1,
				1,
				1
			],
			"localMatrix": {
				"0": 1,
				"1": 0,
				"2": 0,
				"3": 0,
				"4": 0,
				"5": 1,
				"6": 0,
				"7": 0,
				"8": 0,
				"9": 0,
				"10": 1,
				"11": 0,
				"12": 0,
				"13": 0,
				"14": 0,
				"15": 1
			},
			"isEnabled": true,
			"isVisible": true,
			"infiniteDistance": false,
			"pickable": true,
			"receiveShadows": false,
			"billboardMode": 0,
			"visibility": 1,
			"checkCollisions": true,
			"isBlocker": false,
			"overrideMaterialSideOrientation": 0,
			"parentId": "df479701-7d74-4c59-aa4d-693040051dea",
			"isUnIndexed": false,
			"geometryId": "2c986f42-5655-48cd-98b6-8d87f039221a",
			"subMeshes": null,
			"materialId": "934bea4d-b52f-4153-9089-f55a5d628bf7",
			"metadata": {
				"gltf": {
					"pointers": [
						"/meshes/7/primitives/0",
						"/nodes/9"
					]
				},
				"basePoseMatrix": {
					"0": -1,
					"1": 0,
					"2": 0,
					"3": 0,
					"4": 0,
					"5": 1,
					"6": 0,
					"7": 0,
					"8": 0,
					"9": 0,
					"10": 1,
					"11": 0,
					"12": 0,
					"13": -10.062779426574707,
					"14": 0,
					"15": 1
				},
				"originalSourceFile": {
					"id": "PM3D_Cube3D1_11",
					"name": "PM3D_Cube3D1_11",
					"sceneFileName": "prototype.glb"
				},
				"isPickable": true,
				"script": {
					"name": "None"
				},
				"renderingGroupId": 0
			},
			"instances": [],
			"animations": [],
			"ranges": [],
			"layerMask": 268435455,
			"alphaIndex": 1.7976931348623157e+308,
			"hasVertexAlpha": true,
			"overlayAlpha": 0.3,
			"overlayColor": [
				1,
				0,
				0
			],
			"applyFog": true,
			"delayLoadingFile": "geometries/2c986f42-5655-48cd-98b6-8d87f039221a.babylonbinarymeshdata",
			"boundingBoxMaximum": [
				23.73770523071289,
				-6.109528064727783,
				3.5868000984191895
			],
			"boundingBoxMinimum": [
				19.29793930053711,
				-10.109526634216309,
				-0.8529807329177856
			],
			"_binaryInfo": {
				"positionsAttrDesc": {
					"count": 288,
					"stride": 3,
					"offset": 0,
					"dataType": 1
				},
				"normalsAttrDesc": {
					"count": 288,
					"stride": 3,
					"offset": 1152,
					"dataType": 1
				},
				"colorsAttrDesc": {
					"count": 384,
					"stride": 4,
					"offset": 2304,
					"dataType": 1
				},
				"indicesAttrDesc": {
					"count": 144,
					"stride": 1,
					"offset": 3840,
					"dataType": 0
				},
				"subMeshesAttrDesc": {
					"count": 1,
					"stride": 5,
					"offset": 4416,
					"dataType": 0
				}
			},
			"positions": null,
			"normals": null,
			"colors": null,
			"indices": null
		}
	],
	"multiMaterials": [],
	"lods": []
}